filmaster/__init__.py
filmaster/__main__.py
filmaster/bot.py
filmaster/dataset.json
filmaster/nlu.py
filmaster/tmdb.py
nlu_engine/nlu_engine.json
templates/entities.chatl
templates/general.chatl
templates/intents.chatl
templates/synonyms.chatl
filmaster-0.0.7.dist-info/entry_points.txt
filmaster-0.0.7.dist-info/LICENSE.md
filmaster-0.0.7.dist-info/WHEEL
filmaster-0.0.7.dist-info/METADATA
filmaster-0.0.7.dist-info/RECORD
