Metadata-Version: 2.1
Name: filmaster
Version: 0.0.7
Summary: Discord bot that scours TMDB for film info
Home-page: https://gitlab.com/ObserverOfTime/filmaster
License: AFL-3.0
Keywords: discord,ai,nlp,tmdb
Author: ObserverOfTime
Author-email: chronobserver@disroot.org
Requires-Python: >=3.6,<4.0
Classifier: Development Status :: 3 - Alpha
Classifier: Intended Audience :: Education
Classifier: Intended Audience :: End Users/Desktop
Classifier: License :: OSI Approved :: Academic Free License (AFL)
Classifier: Natural Language :: English
Classifier: Operating System :: OS Independent
Classifier: Programming Language :: Python
Classifier: Programming Language :: Python :: 3
Classifier: Programming Language :: Python :: 3 :: Only
Classifier: Programming Language :: Python :: 3.6
Classifier: Programming Language :: Python :: 3.7
Classifier: Programming Language :: Python :: 3.8
Classifier: Topic :: Communications :: Chat
Classifier: Topic :: Internet :: WWW/HTTP :: Indexing/Search
Classifier: Topic :: Scientific/Engineering :: Artificial Intelligence
Requires-Dist: discord.py (>=1.3.1,<2.0.0)
Requires-Dist: isle (>=0.6.0,<0.7.0)
Requires-Dist: snips-nlu (>=0.20.2,<0.21.0)
Project-URL: Documentation, https://observeroftime.gitlab.io/filmaster/
